
import becker.robots.City;
import becker.robots.Direction;
import becker.robots.MazeCity;
import becker.robots.RobotRC;
import becker.robots.RobotSE;
import becker.robots.Sim;
import java.awt.Color;
import java.awt.geom.GeneralPath;

/*
 * To change this template, choose Tools | Templates
 * and open the template in the editor.
 */

/**
 *
 * @author whitb0039
 */
public class TEST {

    /**
     * @param args the command line arguments
     */
    public static void main(String[] args) {
        // TODO code application logic here
        
        City kw = new City();
        
        //AnimatedIcon$a(double d, double d1, double d2, double d3, double d4, Color color)
        
        
        //makre new test robot
        RobotRC test = new RobotRC(kw, 1, 1, Direction.NORTH);
        
        
        
         // <editor-fold defaultstate="collapsed" desc="Compiled Code">
        /* 0: iload_1
         * 1: bipush        109
         * 3: if_icmpeq     12
         * 6: iload_1
         * 7: bipush        77
         * 9: if_icmpne     17
         * 12: aload_0
         * 13: invokevirtual #5                  // Method move:("w")V
         * 16: return
         * 17: iload_1
         * 18: bipush        114
         * 20: if_icmpeq     29
         * 23: iload_1
         * 24: bipush        82
         * 26: if_icmpne     34
         * 29: aload_0
         * 30: invokevirtual #9                  // Method turnRight:("d")V
         * 33: return
         * 34: iload_1
         * 35: bipush        108
         * 37: if_icmpeq     46
         * 40: iload_1
         * 41: bipush        76
         * 43: if_icmpne     51
         * 46: aload_0
         * 47: invokevirtual #8                  // Method turnLeft:("a")V
         * 50: return
         * 51: iload_1
         * 52: bipush        117
         * 54: if_icmpeq     63
         * 57: iload_1
         * 58: bipush        85
         * 60: if_icmpne     68
         * 63: aload_0
         * 64: invokevirtual #6                  // Method pickThing:("c")V
         * 67: return
         * 68: iload_1
         * 69: bipush        100
         * 71: if_icmpeq     80
         * 74: iload_1
         * 75: bipush        68
         * 77: if_icmpne     84
         * 80: aload_0
         * 81: invokevirtual #7                  // Method putThing:("v")V
         * 84: return
         *  */
        // </editor-fold>
        
        
        
        
    }
}
